maschine/__init__.py
maschine/cv.py
maschine/query.py
maschine/rec.py
maschine/rec2.py
maschine/scripta.py
maschine/ttrain.py
programmador/__init__.py
programmador/data_structures.py
programmador/dp.py
programmador/examples.py
programmador/graphs.py
programmador/math_utils.py
programmador/search.py
programmador/sorting.py
quadrado_ml_alg_lib-2.2.4.dist-info/METADATA
quadrado_ml_alg_lib-2.2.4.dist-info/WHEEL
quadrado_ml_alg_lib-2.2.4.dist-info/top_level.txt
quadrado_ml_alg_lib-2.2.4.dist-info/RECORD
