Metadata-Version: 2.2
Name: quadrado-ml-alg-lib
Version: 2.2.4
Summary: LIB FOR ML DEVs
Author: Quadrado
Author-email: cheater22800000@gmail.com
Classifier: Programming Language :: Python :: 3
Classifier: License :: OSI Approved :: MIT License
Classifier: Operating System :: OS Independent
Requires-Python: >=3.6
Dynamic: author
Dynamic: author-email
Dynamic: classifier
Dynamic: description
Dynamic: description-content-type
Dynamic: requires-python
Dynamic: summary
